biblioteca/__init__.py
biblioteca/math.py
biblioteca_de_filip-22.4.0.dist-info/METADATA
biblioteca_de_filip-22.4.0.dist-info/WHEEL
biblioteca_de_filip-22.4.0.dist-info/top_level.txt
biblioteca_de_filip-22.4.0.dist-info/RECORD
