Metadata-Version: 2.1
Name: biblioteca_de_filip
Version: 22.4.0
Summary: Personal Python Library
Home-page: https://github.com/FilipCvetko/biblioteca_de_filip
Author: Filip Cvetko
Author-email: filipcvetko123@gmail.com
License: UNKNOWN
Platform: UNKNOWN
Classifier: Programming Language :: Python :: 3
Classifier: License :: OSI Approved :: MIT License
Classifier: Operating System :: OS Independent
Requires-Python: >=3.6
